iotdb_mcp_server/__init__.py
iotdb_mcp_server/config.py
iotdb_mcp_server/server.py
iotdb_mcp_server-0.2.0.dist-info/METADATA
iotdb_mcp_server-0.2.0.dist-info/WHEEL
iotdb_mcp_server-0.2.0.dist-info/entry_points.txt
iotdb_mcp_server-0.2.0.dist-info/licenses/LICENSE
iotdb_mcp_server-0.2.0.dist-info/RECORD
