Metadata-Version: 2.4
Name: iotdb-mcp-server
Version: 0.2.0
Summary: A Model Context Protocol (MCP) server that enables secure interaction with IoTDB databases. This server allows AI assistants to list tables, read data, and execute SQL queries through a controlled interface, making database exploration and analysis safer and more structured.
License-Expression: Apache-2.0
License-File: LICENSE
Requires-Python: >=3.12
Requires-Dist: apache-iotdb>=2.0.1b0
Requires-Dist: mcp>=1.0.0
